term_background/__init__.py
term_background/__main__.py
term_background/version.py
term_background-1.0.4.dist-info/COPYING
term_background-1.0.4.dist-info/METADATA
term_background-1.0.4.dist-info/WHEEL
term_background-1.0.4.dist-info/top_level.txt
term_background-1.0.4.dist-info/RECORD
